plado/__init__.py
plado/datalog/__init__.py
plado/datalog/numeric.py
plado/datalog/program.py
plado/datalog/evaluator/__init__.py
plado/datalog/evaluator/compiler.py
plado/datalog/evaluator/filtering.py
plado/datalog/evaluator/join_graph.py
plado/datalog/evaluator/planner.py
plado/datalog/evaluator/query_tree.py
plado/datalog/evaluator/query_tree_flattener.py
plado/parser/__init__.py
plado/parser/parser.py
plado/parser/sanity_checks.py
plado/parser/tokenizer.py
plado/pddl/__init__.py
plado/pddl/action.py
plado/pddl/arguments.py
plado/pddl/boolean_expression.py
plado/pddl/derived_predicate.py
plado/pddl/domain.py
plado/pddl/effects.py
plado/pddl/metrics.py
plado/pddl/numeric_expression.py
plado/pddl/problem.py
plado/pddl/type.py
plado/pddl_utils/__init__.py
plado/pddl_utils/normalize.py
plado/pddl_utils/transformers.py
plado/pddl_utils/types.py
plado/pddl_utils/visitors.py
plado/semantics/__init__.py
plado/semantics/applicable_actions_generator.py
plado/semantics/datalog_utils.py
plado/semantics/goal_checker.py
plado/semantics/grounder.py
plado/semantics/successor_generator.py
plado/semantics/task.py
plado/utils/__init__.py
plado/utils/graph.py
plado/utils/numbers.py
plado/utils/search.py
plado/utils/union_find.py
plado-0.1.6.dist-info/METADATA
plado-0.1.6.dist-info/WHEEL
plado-0.1.6.dist-info/licenses/AUTHORS
plado-0.1.6.dist-info/licenses/LICENSE
plado-0.1.6.dist-info/RECORD
