Metadata-Version: 2.4
Name: plado
Version: 0.1.6
Summary: Python utils for lifted PDDL planning, including PDDL parser and lifted successor generation.
Project-URL: Homepage, https://github.com/massle/plado
Project-URL: Issues, https://github.com/massle/plado/issues
Author-email: Marcel Steinmetz <ma.steinm@gmail.com>
License-File: AUTHORS
License-File: LICENSE
Classifier: License :: OSI Approved :: MIT License
Classifier: Operating System :: OS Independent
Classifier: Programming Language :: Python :: 3
Requires-Python: >=3.10
